iflow_mcp_meilisearch_mcp-0.6.0.dist-info/licenses/LICENSE
meilisearch_mcp/__init__.py
meilisearch_mcp/__main__.py
meilisearch_mcp/__version__.py
meilisearch_mcp/chat.py
meilisearch_mcp/client.py
meilisearch_mcp/documents.py
meilisearch_mcp/indexes.py
meilisearch_mcp/keys.py
meilisearch_mcp/logging.py
meilisearch_mcp/monitoring.py
meilisearch_mcp/server.py
meilisearch_mcp/settings.py
meilisearch_mcp/tasks.py
iflow_mcp_meilisearch_mcp-0.6.0.dist-info/METADATA
iflow_mcp_meilisearch_mcp-0.6.0.dist-info/WHEEL
iflow_mcp_meilisearch_mcp-0.6.0.dist-info/entry_points.txt
iflow_mcp_meilisearch_mcp-0.6.0.dist-info/top_level.txt
iflow_mcp_meilisearch_mcp-0.6.0.dist-info/RECORD
